{
  "subtitle": "", 
  "uuid": "4a690f63dcbb4e149100d0db27e2ecd5", 
  "language": "por_PT", 
  "title": "Conhece os teus direitos", 
  "image": "7bc33d95784a4bef9f98acced6dd9588", 
  "_version": {
    "package_version": "1.4.3", 
    "language_version": "2.7.6", 
    "language_version_string": "2.7.6 (default, Jun 22 2015, 18:01:27) \n[GCC 4.8.2]", 
    "language": "python", 
    "package": "elastic-git"
  }, 
  "slug": "conhece-os-teus-direitos", 
  "source": null, 
  "position": 1, 
  "image_host": "http://thumbor.unicore.io", 
  "featured_in_navbar": true, 
  "id": null
}